Metadata-Version: 1.0
Name: cxy-addons
Version: 1.0.0
Summary: this is a niubi lib
Home-page: https://github.com/chenxingyuan/python_code
Author: Sz
Author-email: 2562891194@qq.com
License: MIT
Platform: UNKNOWN
